{
  "criteria": {
    "player_uses_nova_rocket": {
      "trigger": "minecraft:shot_crossbow",
      "conditions": {
        "player": [
          {
            "condition": "minecraft:location_check",
            "predicate": {
              "dimension": "minecraft:overworld"
            }
          }
        ],
        "item": {
          "predicates": {
            "minecraft:custom_data": {
              "id": "nova_rocket"
            }
          }
        }
      }
    }
  },
  "rewards": {
    "function": "custom:event/player_uses_nova_rocket/main"
  }
}
