{
  "condition": "minecraft:any_of",
  "terms": [
    {
      "condition": "minecraft:value_check",
      "range": 1,
      "value": {
        "score": "gamemode_components",
        "target": {
          "name": "$duel_settings_locked",
          "type": "minecraft:fixed"
        },
        "type": "minecraft:score"
      }
    },
    {
      "condition": "minecraft:value_check",
      "range": -1,
      "value": {
        "score": "gamemode_components",
        "target": {
          "name": "$config_override.disable_item_category/utilities",
          "type": "minecraft:fixed"
        },
        "type": "minecraft:score"
      }
    },
    {
      "condition": "minecraft:any_of",
      "terms": [
        {
          "condition": "minecraft:value_check",
          "range": 1,
          "value": {
            "score": "gamemode_components",
            "target": {
              "name": "$item_pool.arrow",
              "type": "minecraft:fixed"
            },
            "type": "minecraft:score"
          }
        },
        {
          "condition": "minecraft:value_check",
          "range": 1,
          "value": {
            "score": "gamemode_components",
            "target": {
              "name": "$item_pool.canopy",
              "type": "minecraft:fixed"
            },
            "type": "minecraft:score"
          }
        },
        {
          "condition": "minecraft:value_check",
          "range": 1,
          "value": {
            "score": "gamemode_components",
            "target": {
              "name": "$item_pool.fireball",
              "type": "minecraft:fixed"
            },
            "type": "minecraft:score"
          }
        },
        {
          "condition": "minecraft:value_check",
          "range": 1,
          "value": {
            "score": "gamemode_components",
            "target": {
              "name": "$item_pool.nova_rocket",
              "type": "minecraft:fixed"
            },
            "type": "minecraft:score"
          }
        },
        {
          "condition": "minecraft:value_check",
          "range": 1,
          "value": {
            "score": "gamemode_components",
            "target": {
              "name": "$item_pool.obsidian_shield",
              "type": "minecraft:fixed"
            },
            "type": "minecraft:score"
          }
        },
        {
          "condition": "minecraft:value_check",
          "range": 1,
          "value": {
            "score": "gamemode_components",
            "target": {
              "name": "$item_pool.shield",
              "type": "minecraft:fixed"
            },
            "type": "minecraft:score"
          }
        },
        {
          "condition": "minecraft:value_check",
          "range": 1,
          "value": {
            "score": "gamemode_components",
            "target": {
              "name": "$item_pool.splash",
              "type": "minecraft:fixed"
            },
            "type": "minecraft:score"
          }
        },
        {
          "condition": "minecraft:value_check",
          "range": 1,
          "value": {
            "score": "gamemode_components",
            "target": {
              "name": "$item_pool.vortex",
              "type": "minecraft:fixed"
            },
            "type": "minecraft:score"
          }
        }
      ]
    }
  ]
}
