{
  "pools": [
    {
      "entries": [
        {
          "functions": [
            {
              "components": {
                "custom_data": {
                  "id": "nova_rocket/firework_rocket",
                  "nova_rocket": {
                    "firework_rocket": true
                  }
                },
                "minecraft:custom_model_data": {
                  "strings": [
                    "rocketriders",
                    "nova_rocket/firework_rocket",
                    "white"
                  ]
                },
                "minecraft:fireworks": {
                  "explosions": [
                    {
                      "colors": [
                        15790320
                      ],
                      "fade_colors": [
                        11743532,
                        3887386,
                        2437522,
                        8073150,
                        2651799,
                        14188952,
                        4312372,
                        14602026,
                        6719955,
                        12801229,
                        15435844
                      ],
                      "has_trail": true,
                      "has_twinkle": true,
                      "shape": "small_ball"
                    }
                  ],
                  "flight_duration": 2
                }
              },
              "function": "minecraft:set_components"
            },
            {
              "components": {
                "minecraft:fireworks": {
                  "explosions": [
                    {
                      "colors": [
                        2437522,
                        2651799
                      ],
                      "has_trail": true,
                      "has_twinkle": true,
                      "shape": "small_ball"
                    }
                  ],
                  "flight_duration": 3
                }
              },
              "conditions": [
                {
                  "condition": "minecraft:inverted",
                  "term": {
                    "condition": "minecraft:reference",
                    "name": "game:match_components/neutral_items"
                  }
                },
                {
                  "condition": "minecraft:reference",
                  "name": "game:blue_team_skin/blue"
                },
                {
                  "condition": "minecraft:reference",
                  "name": "custom:team/blue"
                }
              ],
              "function": "minecraft:set_components"
            },
            {
              "components": {
                "minecraft:fireworks": {
                  "explosions": [
                    {
                      "colors": [
                        16711680,
                        16744319
                      ],
                      "has_trail": true,
                      "has_twinkle": true,
                      "shape": "small_ball"
                    }
                  ],
                  "flight_duration": 3
                }
              },
              "conditions": [
                {
                  "condition": "minecraft:inverted",
                  "term": {
                    "condition": "minecraft:reference",
                    "name": "game:match_components/neutral_items"
                  }
                },
                {
                  "condition": "minecraft:reference",
                  "name": "game:blue_team_skin/any_red_skin"
                },
                {
                  "condition": "minecraft:reference",
                  "name": "custom:team/blue"
                }
              ],
              "function": "minecraft:set_components"
            },
            {
              "components": {
                "minecraft:fireworks": {
                  "explosions": [
                    {
                      "colors": [
                        14602026,
                        15435844
                      ],
                      "has_trail": true,
                      "has_twinkle": true,
                      "shape": "small_ball"
                    }
                  ],
                  "flight_duration": 3
                }
              },
              "conditions": [
                {
                  "condition": "minecraft:inverted",
                  "term": {
                    "condition": "minecraft:reference",
                    "name": "game:match_components/neutral_items"
                  }
                },
                {
                  "condition": "minecraft:reference",
                  "name": "game:yellow_team_skin/yellow"
                },
                {
                  "condition": "minecraft:reference",
                  "name": "custom:team/yellow"
                }
              ],
              "function": "minecraft:set_components"
            },
            {
              "components": {
                "minecraft:fireworks": {
                  "explosions": [
                    {
                      "colors": [
                        3887386,
                        4312372
                      ],
                      "has_trail": true,
                      "has_twinkle": true,
                      "shape": "small_ball"
                    }
                  ],
                  "flight_duration": 3
                }
              },
              "conditions": [
                {
                  "condition": "minecraft:inverted",
                  "term": {
                    "condition": "minecraft:reference",
                    "name": "game:match_components/neutral_items"
                  }
                },
                {
                  "condition": "minecraft:reference",
                  "name": "game:yellow_team_skin/green"
                },
                {
                  "condition": "minecraft:reference",
                  "name": "custom:team/yellow"
                }
              ],
              "function": "minecraft:set_components"
            },
            {
              "function": "minecraft:reference",
              "name": "items:set_custom_model_data"
            }
          ],
          "name": "minecraft:firework_rocket",
          "type": "minecraft:item"
        }
      ],
      "rolls": 1
    }
  ]
}
